witsml20/__init__.py
witsml20/absolute_pressure.py
witsml20/absorbed_dose_measure.py
witsml20/absorbed_dose_measure_ext.py
witsml20/absorbed_dose_uom.py
witsml20/abstract_activity_parameter.py
witsml20/abstract_boolean_array.py
witsml20/abstract_bottom_hole_temperature.py
witsml20/abstract_cement_job.py
witsml20/abstract_cement_stage.py
witsml20/abstract_connection_type.py
witsml20/abstract_contextual_object.py
witsml20/abstract_coordinate_operation_type.py
witsml20/abstract_coordinate_system_type.py
witsml20/abstract_data_object.py
witsml20/abstract_dq_element_type.py
witsml20/abstract_dq_positional_accuracy_type.py
witsml20/abstract_dq_result_type.py
witsml20/abstract_event_extension.py
witsml20/abstract_ex_geographic_extent_type.py
witsml20/abstract_floating_point_array.py
witsml20/abstract_general_conversion_type.py
witsml20/abstract_geodetic_crs.py
witsml20/abstract_gmltype.py
witsml20/abstract_graphical_information.py
witsml20/abstract_index_value.py
witsml20/abstract_integer_array.py
witsml20/abstract_iscwsa_error_coefficient.py
witsml20/abstract_item_wt_or_vol_per_unit.py
witsml20/abstract_log_data_context.py
witsml20/abstract_numeric_array.py
witsml20/abstract_object.py
witsml20/abstract_object_type.py
witsml20/abstract_parameter_key.py
witsml20/abstract_pressure_value.py
witsml20/abstract_projected_crs.py
witsml20/abstract_rotary_steerable_tool.py
witsml20/abstract_string_array.py
witsml20/abstract_temperature_pressure.py
witsml20/abstract_time_object_type.py
witsml20/abstract_time_primitive_type.py
witsml20/abstract_value_array.py
witsml20/abstract_vertical_crs.py
witsml20/abstract_well_location.py
witsml20/acidizefrac_extension.py
witsml20/activity.py
witsml20/activity_of_radioactivity_measure.py
witsml20/activity_of_radioactivity_measure_ext.py
witsml20/activity_of_radioactivity_uom.py
witsml20/activity_template.py
witsml20/actuate_value.py
witsml20/aggregation_type.py
witsml20/amount_of_substance_measure.py
witsml20/amount_of_substance_measure_ext.py
witsml20-1.0.0.dist-info/LICENSE
witsml20-1.0.0.dist-info/WHEEL
witsml20-1.0.0.dist-info/METADATA
witsml20-1.0.0.dist-info/RECORD
